      
{
  "stops": [
    {
      "stop": "rgba(100, 115, 178,0.01)",
      "value": 0
    },
    {
      "stop": "rgba(90, 93, 153,0.01)",
      "value": 2
    },
    {
      "stop": "rgba(79, 105, 177,0.02)",
      "value": 4
    },
    {
      "stop": "rgba(85, 137, 176,0.03)",
      "value": 6
    },
    {
      "stop": "rgba(103, 166, 151,0.03)",
      "value": 8
    },
    {
      "stop": "rgba(109, 179, 104,0.05)",
      "value": 10
    },
    {
      "stop": "rgba(255, 231, 109,0.05)",
      "value": 15
    },
    {
      "stop": "rgba(249, 136, 41,0.1)",
      "value": 20
    },
    {
      "stop": "rgba(238, 102, 55,0.13)",
      "value": 25
    },
    {
      "stop": "rgba(225, 35, 35,0.16)",
      "value": 30
    },
    {
      "stop": "rgba(202, 0, 149,0.2)",
      "value": 40
    },
    {
      "stop": "rgba(119, 12, 99,0.3)",
      "value": 50
    },
    {
      "stop": "rgba(49, 0, 46,0.3)",
      "value": 60
    }
  ],
  "fieldName": "0"
}

    